metapensiero/markup/semtext/__init__.py
metapensiero/markup/semtext/ast.py
metapensiero/markup/semtext/exc.py
metapensiero/markup/semtext/html.py
metapensiero/markup/semtext/lexer.py
metapensiero/markup/semtext/parser.py
metapensiero/markup/semtext/quill.py
metapensiero/markup/semtext/text.py
metapensiero/markup/semtext/visitor.py
metapensiero_markup_semtext-1.0.dist-info/METADATA
metapensiero_markup_semtext-1.0.dist-info/WHEEL
metapensiero_markup_semtext-1.0.dist-info/entry_points.txt
metapensiero_markup_semtext-1.0.dist-info/RECORD
