Metadata-Version: 2.1
Name: metapensiero.markup.semtext
Version: 1.0
Summary: a Simple Enough Markup
Author-Email: Lele Gaifax <lele@metapensiero.it>
License: GPL-3.0-or-later
Classifier: Development Status :: 4 - Beta
Classifier: Programming Language :: Python
Classifier: Programming Language :: Python :: 3
Classifier: Programming Language :: Python :: 3.11
Classifier: Programming Language :: Python :: 3.12
Classifier: Intended Audience :: Developers
Classifier: License :: OSI Approved :: GNU General Public License v3 or later (GPLv3+)
Project-URL: Source, https://gitlab.com/metapensiero/metapensiero.markup.semtext
Project-URL: Changelog, https://gitlab.com/metapensiero/metapensiero.markup.semtext/-/blob/master/CHANGES.rst
Requires-Python: >=3.11
Requires-Dist: lxml
Requires-Dist: sly
Provides-Extra: dev
Requires-Dist: build; extra == "dev"
Requires-Dist: bump-my-version; extra == "dev"
Requires-Dist: readme_renderer; extra == "dev"
Requires-Dist: twine; extra == "dev"
